tot/__init__.py
tot/models.py
tot/data/24/24.csv
tot/data/crosswords/mini0505.json
tot/data/crosswords/mini0505_0_100_5.json
tot/data/text/data_100_random_text.txt
tot/methods/bfs.py
tot/prompts/crosswords.py
tot/prompts/game24.py
tot/prompts/text.py
tot/tasks/__init__.py
tot/tasks/base.py
tot/tasks/crosswords.py
tot/tasks/game24.py
tot/tasks/text.py
tree_of_thoughts_llm-0.1.0.dist-info/LICENSE
tree_of_thoughts_llm-0.1.0.dist-info/METADATA
tree_of_thoughts_llm-0.1.0.dist-info/WHEEL
tree_of_thoughts_llm-0.1.0.dist-info/top_level.txt
tree_of_thoughts_llm-0.1.0.dist-info/RECORD
