Metadata-Version: 2.1
Name: tree-of-thoughts-llm
Version: 0.1.0
Summary: Official Implementation of "Tree of Thoughts: Deliberate Problem Solving with Large Language Models"
Home-page: https://github.com/princeton-nlp/tree-of-thought-llm
Author: Shunyu Yao
Author-email: Shunyu Yao <shunyuyao.cs@gmail.com>
License: MIT License
Project-URL: Homepage, https://github.com/princeton-nlp/tree-of-thought-llm
Keywords: tree-search,large-language-models,llm,prompting,tree-of-thoughts
Classifier: License :: OSI Approved :: MIT License
Classifier: Programming Language :: Python :: 3
Classifier: Programming Language :: Python :: 3.7
Classifier: Programming Language :: Python :: 3.8
Classifier: Programming Language :: Python :: 3.9
Classifier: Programming Language :: Python :: 3.10
Classifier: Programming Language :: Python :: 3.11
Classifier: Intended Audience :: Science/Research
Classifier: Topic :: Scientific/Engineering :: Artificial Intelligence
Requires-Python: >=3.7
License-File: LICENSE
Requires-Dist: aiohttp (==3.8.4)
Requires-Dist: aiosignal (==1.3.1)
Requires-Dist: async-timeout (==4.0.2)
Requires-Dist: attrs (==23.1.0)
Requires-Dist: backoff (==2.2.1)
Requires-Dist: certifi (==2023.5.7)
Requires-Dist: charset-normalizer (==3.1.0)
Requires-Dist: frozenlist (==1.3.3)
Requires-Dist: idna (==3.4)
Requires-Dist: mpmath (==1.3.0)
Requires-Dist: multidict (==6.0.4)
Requires-Dist: numpy (==1.24.3)
Requires-Dist: openai (==0.27.7)
Requires-Dist: requests (==2.31.0)
Requires-Dist: sympy (==1.12)
Requires-Dist: tqdm (==4.65.0)
Requires-Dist: urllib3 (==2.0.2)
Requires-Dist: yarl (==1.9.2)
Requires-Dist: pandas (==2.0.3)
